README.md
setup.py
drf_companion/__init__.py
drf_companion/api.py
drf_companion.egg-info/PKG-INFO
drf_companion.egg-info/SOURCES.txt
drf_companion.egg-info/dependency_links.txt
drf_companion.egg-info/requires.txt
drf_companion.egg-info/top_level.txt