Metadata-Version: 1.2
Name: drf-companion
Version: 1.0.1
Summary: A simple Python package to facilitate interactions with DRF APIs
Home-page: https://github.com/jjorissen52/apprest_interface
Author: John-Paul Jorissen
Author-email: jjorissen52@gmail.com
License: Apache
Keywords: Django REST Framework DRF WebServices API
Platform: UNKNOWN
Classifier: Development Status :: 4 - Beta
Classifier: Intended Audience :: Developers
Classifier: Programming Language :: Python :: 3.6
Classifier: Operating System :: Microsoft :: Windows :: Windows 10
Classifier: Operating System :: POSIX :: Linux
Classifier: License :: OSI Approved :: Apache Software License
Classifier: Programming Language :: Python :: 3.6
Requires-Python: >=3.6
